{
  "status": "success",
  "elapsed_sec": 0.34,
  "data": {
    "ok": true,
    "status": "ok",
    "message": "forecast completed",
    "request_id": "77449cd8-8d97-498f-a700-b109df6b3733",
    "timestamp": "2026-02-24T03:51:03Z",
    "request": {
      "symbol": "BTC/USD",
      "timeframe": "1h",
      "horizons": [
        24
      ],
      "use_montecarlo": true,
      "paths": 1000,
      "trade_mode": "forward",
      "include_predictions": true,
      "include_metadata": true,
      "include_model_info": true,
      "execution_price": 114437.47
    },
    "warnings": [],
    "data": {
      "payload": {
        "symbol": "BTC/USD",
        "asOf": "2025-10-28T01:00:00+00:00",
        "timeframe": "1h",
        "use_montecarlo": true,
        "horizons": [
          {
            "h": "24h",
            "direction": "long",
            "trade_mode": "forward",
            "entry_price": 116956.07271830013,
            "entry_type": "conditional_forecast",
            "entry_method": "median",
            "forecast": {
              "medianPrice": 116956.07271830013,
              "p20": 114635.88988662872,
              "p80": 118812.1807254197
            },
            "tp": 118812.1807254197,
            "sl": 114635.88988662872,
            "riskReward": 0.8,
            "prob_hit_tp_before_sl": 0.505,
            "confidence": 0.6441,
            "position_size": 1.0,
            "model": {
              "mean": "NHITS",
              "vol": "EGARCH_t",
              "calibrated": true
            }
          }
        ],
        "entry_price": 116956.07271830013
      },
      "as_of": "2025-10-28T01:00:00+00:00",
      "data_hash": "30f23d7b7bb37a1a84842d577314dd099640b49531c0ec52c9493a7438e372bc",
      "durations": {
        "fetch_seconds": 0.0004206000012345612,
        "mean_model_fit_seconds": 0.0,
        "garch_fit_seconds": 0.0,
        "garch_forecast_seconds": 0.12978719995589927,
        "monte_carlo_seconds": 0.0027048999327234924,
        "forecast_loop_seconds": 0.06278959999326617,
        "total_seconds": 0.34204169997246936
      }
    },
    "metadata": {
      "symbol": "BTC/USD",
      "timeframe": "1h",
      "horizons": [
        24
      ],
      "timestamp": "2026-02-24T03:51:02Z",
      "timestamp_slug": "20260224T035102Z",
      "as_of": "2025-10-28T01:00:00+00:00",
      "n_observations": 202,
      "data_hash": "30f23d7b7bb37a1a84842d577314dd099640b49531c0ec52c9493a7438e372bc",
      "use_montecarlo": true,
      "monte_carlo_paths": 200,
      "durations": {
        "fetch_seconds": 0.0004206000012345612,
        "mean_model_fit_seconds": 0.0,
        "garch_fit_seconds": 0.0,
        "garch_forecast_seconds": 0.12978719995589927,
        "monte_carlo_seconds": 0.0027048999327234924,
        "forecast_loop_seconds": 0.06278959999326617,
        "total_seconds": 0.34204169997246936
      },
      "mean_model": {
        "name": "NHITS",
        "class": "NHiTSForecaster",
        "backend_class": "NHiTSModel",
        "hyperparameters": {
          "output_chunk_shift": 0,
          "num_stacks": 3,
          "num_blocks": 1,
          "num_layers": 2,
          "layer_widths": 512,
          "pooling_kernel_sizes": null,
          "n_freq_downsample": null,
          "dropout": 0.1,
          "activation": "ReLU",
          "MaxPool1d": true,
          "input_chunk_length": 48,
          "output_chunk_length": 24,
          "n_epochs": 100,
          "batch_size": 20000,
          "random_state": 42,
          "loss_fn": {
            "training": false,
            "reduction": "mean",
            "beta": 1.0
          },
          "optimizer_kwargs": {
            "lr": 0.001
          },
          "pl_trainer_kwargs": {
            "accelerator": "gpu",
            "devices": 1
          }
        }
      },
      "vol_model": {
        "class": "EGARCHVolModel",
        "distribution": "Student-t",
        "degrees_of_freedom": 6.0,
        "skew": -0.8,
        "forecast_method": "simulation",
        "sigma_last": 0.005
      },
      "environment": {
        "python": "3.12.10",
        "numpy": "1.26.4",
        "pandas": "2.3.3",
        "platform": "Windows-11-10.0.26200-SP0"
      },
      "regime": {
        "enabled": true,
        "label": "TREND_UP",
        "confidence": 4.879737271825469e-11,
        "lookback": 200,
        "route": "trend"
      },
      "residual_std": 0.004418562720291921,
      "last_price": 114437.47,
      "execution_price": 114437.47,
      "price_modeling": 114437.47,
      "price_execution": 114437.47,
      "execution_price_source": "client",
      "sigma_path_min": 0.005,
      "sigma_path_max": 0.005,
      "backtest_time_travel": true,
      "backtest_time_travel_model": "nhits"
    },
    "model_status": {
      "model_type": "nhits",
      "device": "cuda",
      "mean": {
        "loaded": true,
        "reason": "time_travel_cache"
      },
      "vol": {
        "loaded": false,
        "reason": "time_travel_cache"
      }
    },
    "total_seconds": 0.344
  }
}