{
  "status": "success",
  "elapsed_sec": 0.33,
  "data": {
    "ok": true,
    "status": "ok",
    "message": "forecast completed",
    "request_id": "786f56a0-f7c5-48fa-a9f7-6030d34d87de",
    "timestamp": "2026-02-24T04:38:42Z",
    "request": {
      "symbol": "BTC/USD",
      "timeframe": "1h",
      "horizons": [
        24
      ],
      "use_montecarlo": true,
      "paths": 1000,
      "trade_mode": "forward",
      "include_predictions": true,
      "include_metadata": true,
      "include_model_info": true,
      "execution_price": 88688.15
    },
    "warnings": [],
    "data": {
      "payload": {
        "symbol": "BTC/USD",
        "asOf": "2025-12-26T10:00:00+00:00",
        "timeframe": "1h",
        "use_montecarlo": true,
        "horizons": [
          {
            "h": "24h",
            "direction": "long",
            "trade_mode": "forward",
            "entry_price": 89471.31653649843,
            "entry_type": "conditional_forecast",
            "entry_method": "median",
            "forecast": {
              "medianPrice": 89471.31653649843,
              "p20": 87858.61001208832,
              "p80": 90844.9649714203
            },
            "tp": 90844.9649714203,
            "sl": 87858.61001208832,
            "riskReward": 0.8518,
            "prob_hit_tp_before_sl": 0.255,
            "confidence": 0.6441,
            "position_size": 1.0,
            "model": {
              "mean": "NHITS",
              "vol": "EGARCH_t",
              "calibrated": true
            }
          }
        ],
        "entry_price": 89471.31653649843
      },
      "as_of": "2025-12-26T10:00:00+00:00",
      "data_hash": "2e25895483ab4a69bf52269e21466769b4b62391e1bed64b52282207c4a6db8f",
      "durations": {
        "fetch_seconds": 0.0006555000436492264,
        "mean_model_fit_seconds": 0.0,
        "garch_fit_seconds": 0.0,
        "garch_forecast_seconds": 0.12641419999999925,
        "monte_carlo_seconds": 0.002755400026217103,
        "forecast_loop_seconds": 0.06852799997432157,
        "total_seconds": 0.32922130002407357
      }
    },
    "metadata": {
      "symbol": "BTC/USD",
      "timeframe": "1h",
      "horizons": [
        24
      ],
      "timestamp": "2026-02-24T04:38:42Z",
      "timestamp_slug": "20260224T043842Z",
      "as_of": "2025-12-26T10:00:00+00:00",
      "n_observations": 627,
      "data_hash": "2e25895483ab4a69bf52269e21466769b4b62391e1bed64b52282207c4a6db8f",
      "use_montecarlo": true,
      "monte_carlo_paths": 200,
      "durations": {
        "fetch_seconds": 0.0006555000436492264,
        "mean_model_fit_seconds": 0.0,
        "garch_fit_seconds": 0.0,
        "garch_forecast_seconds": 0.12641419999999925,
        "monte_carlo_seconds": 0.002755400026217103,
        "forecast_loop_seconds": 0.06852799997432157,
        "total_seconds": 0.32922130002407357
      },
      "mean_model": {
        "name": "NHITS",
        "class": "NHiTSForecaster",
        "backend_class": "NHiTSModel",
        "hyperparameters": {
          "output_chunk_shift": 0,
          "num_stacks": 3,
          "num_blocks": 1,
          "num_layers": 2,
          "layer_widths": 512,
          "pooling_kernel_sizes": null,
          "n_freq_downsample": null,
          "dropout": 0.1,
          "activation": "ReLU",
          "MaxPool1d": true,
          "input_chunk_length": 48,
          "output_chunk_length": 24,
          "n_epochs": 150,
          "batch_size": 20000,
          "random_state": 42,
          "loss_fn": {
            "training": false,
            "reduction": "mean",
            "beta": 1.0
          },
          "optimizer_kwargs": {
            "lr": 0.001
          },
          "pl_trainer_kwargs": {
            "accelerator": "gpu",
            "devices": 1
          }
        }
      },
      "vol_model": {
        "class": "EGARCHVolModel",
        "distribution": "Student-t",
        "degrees_of_freedom": 6.0,
        "skew": -0.8,
        "forecast_method": "simulation",
        "sigma_last": 0.005
      },
      "environment": {
        "python": "3.12.10",
        "numpy": "1.26.4",
        "pandas": "2.3.3",
        "platform": "Windows-11-10.0.26200-SP0"
      },
      "regime": {
        "enabled": true,
        "label": "TREND_UP",
        "confidence": 1.7006791455176086e-06,
        "lookback": 200,
        "route": "trend"
      },
      "residual_std": 0.0050423570576727215,
      "last_price": 88688.15,
      "execution_price": 88688.15,
      "price_modeling": 88688.15,
      "price_execution": 88688.15,
      "execution_price_source": "client",
      "sigma_path_min": 0.005,
      "sigma_path_max": 0.005,
      "backtest_time_travel": true,
      "backtest_time_travel_model": "nhits"
    },
    "model_status": {
      "model_type": "nhits",
      "device": "cuda",
      "mean": {
        "loaded": true,
        "reason": "time_travel_cache"
      },
      "vol": {
        "loaded": false,
        "reason": "time_travel_cache"
      }
    },
    "total_seconds": 0.332
  }
}