{
  "status": "success",
  "elapsed_sec": 0.43,
  "data": {
    "ok": true,
    "status": "ok",
    "message": "forecast completed",
    "request_id": "36aa97dd-2ccd-4f33-aac6-d90267801a90",
    "timestamp": "2026-02-24T03:53:15Z",
    "request": {
      "symbol": "BTC/USD",
      "timeframe": "1h",
      "horizons": [
        24
      ],
      "use_montecarlo": true,
      "paths": 1000,
      "trade_mode": "forward",
      "include_predictions": true,
      "include_metadata": true,
      "include_model_info": true,
      "execution_price": 119309.87
    },
    "warnings": [],
    "data": {
      "payload": {
        "symbol": "BTC/USD",
        "asOf": "2025-07-17T17:00:00+00:00",
        "timeframe": "1h",
        "use_montecarlo": true,
        "horizons": [
          {
            "h": "24h",
            "direction": "short",
            "trade_mode": "forward",
            "entry_price": 118640.34716622144,
            "entry_type": "conditional_forecast",
            "entry_method": "median",
            "forecast": {
              "medianPrice": 118640.34716622144,
              "p20": 116491.24600528483,
              "p80": 120335.98333292404
            },
            "tp": 116491.24600528483,
            "sl": 120335.98333292404,
            "riskReward": 1.2674,
            "prob_hit_tp_before_sl": 0.0,
            "confidence": 0.6441,
            "position_size": 1.0,
            "model": {
              "mean": "regime_mean_reversion",
              "vol": "EGARCH_t",
              "calibrated": true
            }
          }
        ],
        "entry_price": 118640.34716622144
      },
      "as_of": "2025-07-17T17:00:00+00:00",
      "data_hash": "5b9ebd71c215cd6731d16ce75fb1b5a33d5ff56eb157aa7724d261755ec09ecf",
      "durations": {
        "fetch_seconds": 0.0009371000342071056,
        "mean_model_fit_seconds": 0.00025430001551285386,
        "garch_fit_seconds": 0.0,
        "garch_forecast_seconds": 0.2071649000281468,
        "monte_carlo_seconds": 0.003652999992482364,
        "forecast_loop_seconds": 0.007295899966266006,
        "total_seconds": 0.42456319998018444
      }
    },
    "metadata": {
      "symbol": "BTC/USD",
      "timeframe": "1h",
      "horizons": [
        24
      ],
      "timestamp": "2026-02-24T03:53:14Z",
      "timestamp_slug": "20260224T035314Z",
      "as_of": "2025-07-17T17:00:00+00:00",
      "n_observations": 751,
      "data_hash": "5b9ebd71c215cd6731d16ce75fb1b5a33d5ff56eb157aa7724d261755ec09ecf",
      "use_montecarlo": true,
      "monte_carlo_paths": 200,
      "durations": {
        "fetch_seconds": 0.0009371000342071056,
        "mean_model_fit_seconds": 0.00025430001551285386,
        "garch_fit_seconds": 0.0,
        "garch_forecast_seconds": 0.2071649000281468,
        "monte_carlo_seconds": 0.003652999992482364,
        "forecast_loop_seconds": 0.007295899966266006,
        "total_seconds": 0.42456319998018444
      },
      "mean_model": {
        "name": "regime_mean_reversion",
        "class": "MeanReversionForecaster"
      },
      "vol_model": {
        "class": "EGARCHVolModel",
        "distribution": "Student-t",
        "degrees_of_freedom": 6.0,
        "skew": -0.8,
        "forecast_method": "simulation",
        "sigma_last": 0.005
      },
      "environment": {
        "python": "3.12.10",
        "numpy": "1.26.4",
        "pandas": "2.3.3",
        "platform": "Windows-11-10.0.26200-SP0"
      },
      "regime": {
        "enabled": true,
        "label": "RANGE",
        "confidence": 0.9456861803189613,
        "lookback": 200,
        "route": "alternate"
      },
      "residual_std": 0.003594183040242317,
      "last_price": 119309.87,
      "execution_price": 119309.87,
      "price_modeling": 119309.87,
      "price_execution": 119309.87,
      "execution_price_source": "client",
      "sigma_path_min": 0.005,
      "sigma_path_max": 0.005,
      "backtest_time_travel": true,
      "backtest_time_travel_model": "nhits"
    },
    "model_status": {
      "model_type": "nhits",
      "device": "cuda",
      "mean": {
        "loaded": true,
        "reason": "time_travel_cache"
      },
      "vol": {
        "loaded": false,
        "reason": "time_travel_cache"
      }
    },
    "total_seconds": 0.429
  }
}