{
  "status": "success",
  "elapsed_sec": 0.33,
  "data": {
    "ok": true,
    "status": "ok",
    "message": "forecast completed",
    "request_id": "75272bd5-b4bc-4866-855c-7ba6b6ae259d",
    "timestamp": "2026-02-24T04:39:39Z",
    "request": {
      "symbol": "BTC/USD",
      "timeframe": "1h",
      "horizons": [
        24
      ],
      "use_montecarlo": true,
      "paths": 1000,
      "trade_mode": "forward",
      "include_predictions": true,
      "include_metadata": true,
      "include_model_info": true,
      "execution_price": 90384.87
    },
    "warnings": [],
    "data": {
      "payload": {
        "symbol": "BTC/USD",
        "asOf": "2025-11-19T05:00:00+00:00",
        "timeframe": "1h",
        "use_montecarlo": true,
        "horizons": [
          {
            "h": "24h",
            "direction": "short",
            "trade_mode": "forward",
            "entry_price": 90157.03092627015,
            "entry_type": "conditional_forecast",
            "entry_method": "median",
            "forecast": {
              "medianPrice": 90157.03092627015,
              "p20": 88638.85347073335,
              "p80": 91570.71359756701
            },
            "tp": 88638.85347073335,
            "sl": 91570.71359756701,
            "riskReward": 1.0739,
            "prob_hit_tp_before_sl": 0.0,
            "confidence": 0.6441,
            "position_size": 1.0,
            "model": {
              "mean": "NHITS",
              "vol": "EGARCH_t",
              "calibrated": true
            }
          }
        ],
        "entry_price": 90157.03092627015
      },
      "as_of": "2025-11-19T05:00:00+00:00",
      "data_hash": "2b6bd440e2d74ac9753512d1208a8905f32f6a26cec7d007fe9cf4cf060a45cc",
      "durations": {
        "fetch_seconds": 0.0009312999900430441,
        "mean_model_fit_seconds": 0.0,
        "garch_fit_seconds": 0.0,
        "garch_forecast_seconds": 0.1257507999544032,
        "monte_carlo_seconds": 0.0019234999781474471,
        "forecast_loop_seconds": 0.051990200008731335,
        "total_seconds": 0.32675329997437075
      }
    },
    "metadata": {
      "symbol": "BTC/USD",
      "timeframe": "1h",
      "horizons": [
        24
      ],
      "timestamp": "2026-02-24T04:39:39Z",
      "timestamp_slug": "20260224T043939Z",
      "as_of": "2025-11-19T05:00:00+00:00",
      "n_observations": 734,
      "data_hash": "2b6bd440e2d74ac9753512d1208a8905f32f6a26cec7d007fe9cf4cf060a45cc",
      "use_montecarlo": true,
      "monte_carlo_paths": 200,
      "durations": {
        "fetch_seconds": 0.0009312999900430441,
        "mean_model_fit_seconds": 0.0,
        "garch_fit_seconds": 0.0,
        "garch_forecast_seconds": 0.1257507999544032,
        "monte_carlo_seconds": 0.0019234999781474471,
        "forecast_loop_seconds": 0.051990200008731335,
        "total_seconds": 0.32675329997437075
      },
      "mean_model": {
        "name": "NHITS",
        "class": "NHiTSForecaster",
        "backend_class": "NHiTSModel",
        "hyperparameters": {
          "output_chunk_shift": 0,
          "num_stacks": 3,
          "num_blocks": 1,
          "num_layers": 2,
          "layer_widths": 512,
          "pooling_kernel_sizes": null,
          "n_freq_downsample": null,
          "dropout": 0.1,
          "activation": "ReLU",
          "MaxPool1d": true,
          "input_chunk_length": 48,
          "output_chunk_length": 24,
          "n_epochs": 150,
          "batch_size": 20000,
          "random_state": 42,
          "loss_fn": {
            "training": false,
            "reduction": "mean",
            "beta": 1.0
          },
          "optimizer_kwargs": {
            "lr": 0.001
          },
          "pl_trainer_kwargs": {
            "accelerator": "gpu",
            "devices": 1
          }
        }
      },
      "vol_model": {
        "class": "EGARCHVolModel",
        "distribution": "Student-t",
        "degrees_of_freedom": 6.0,
        "skew": -0.8,
        "forecast_method": "simulation",
        "sigma_last": 0.005
      },
      "environment": {
        "python": "3.12.10",
        "numpy": "1.26.4",
        "pandas": "2.3.3",
        "platform": "Windows-11-10.0.26200-SP0"
      },
      "regime": {
        "enabled": true,
        "label": "TREND_DOWN",
        "confidence": 0.0,
        "lookback": 200,
        "route": "trend"
      },
      "residual_std": 0.0049651837436870605,
      "last_price": 90384.87,
      "execution_price": 90384.87,
      "price_modeling": 90384.87,
      "price_execution": 90384.87,
      "execution_price_source": "client",
      "sigma_path_min": 0.005,
      "sigma_path_max": 0.005,
      "backtest_time_travel": true,
      "backtest_time_travel_model": "nhits"
    },
    "model_status": {
      "model_type": "nhits",
      "device": "cuda",
      "mean": {
        "loaded": true,
        "reason": "time_travel_cache"
      },
      "vol": {
        "loaded": false,
        "reason": "time_travel_cache"
      }
    },
    "total_seconds": 0.329
  }
}