{
  "status": "success",
  "elapsed_sec": 0.44,
  "data": {
    "ok": true,
    "status": "ok",
    "message": "forecast completed",
    "request_id": "2143ae49-04b2-439b-b959-3020c4f856b5",
    "timestamp": "2026-02-24T03:54:13Z",
    "request": {
      "symbol": "BTC/USD",
      "timeframe": "1h",
      "horizons": [
        24
      ],
      "use_montecarlo": true,
      "paths": 1000,
      "trade_mode": "forward",
      "include_predictions": true,
      "include_metadata": true,
      "include_model_info": true,
      "execution_price": 114756.98
    },
    "warnings": [],
    "data": {
      "payload": {
        "symbol": "BTC/USD",
        "asOf": "2025-10-13T16:00:00+00:00",
        "timeframe": "1h",
        "use_montecarlo": true,
        "horizons": [
          {
            "h": "24h",
            "direction": "short",
            "trade_mode": "forward",
            "entry_price": 113637.90592218873,
            "entry_type": "conditional_forecast",
            "entry_method": "median",
            "forecast": {
              "medianPrice": 113637.90592218873,
              "p20": 111718.89786468976,
              "p80": 115182.33233988022
            },
            "tp": 111718.89786468976,
            "sl": 115182.33233988022,
            "riskReward": 1.2425,
            "prob_hit_tp_before_sl": 0.0,
            "confidence": 0.6441,
            "position_size": 1.0,
            "model": {
              "mean": "regime_mean_reversion",
              "vol": "EGARCH_t",
              "calibrated": true
            }
          }
        ],
        "entry_price": 113637.90592218873
      },
      "as_of": "2025-10-13T16:00:00+00:00",
      "data_hash": "104e407e178f067f2090a11a9c18ee8fccc78b2d8eafbda2a2ec3031743496ee",
      "durations": {
        "fetch_seconds": 0.0006387999746948481,
        "mean_model_fit_seconds": 0.00025510002160444856,
        "garch_fit_seconds": 0.0,
        "garch_forecast_seconds": 0.19610480003757402,
        "monte_carlo_seconds": 0.004093399969860911,
        "forecast_loop_seconds": 0.009261300030630082,
        "total_seconds": 0.4358557999948971
      }
    },
    "metadata": {
      "symbol": "BTC/USD",
      "timeframe": "1h",
      "horizons": [
        24
      ],
      "timestamp": "2026-02-24T03:54:13Z",
      "timestamp_slug": "20260224T035413Z",
      "as_of": "2025-10-13T16:00:00+00:00",
      "n_observations": 862,
      "data_hash": "104e407e178f067f2090a11a9c18ee8fccc78b2d8eafbda2a2ec3031743496ee",
      "use_montecarlo": true,
      "monte_carlo_paths": 200,
      "durations": {
        "fetch_seconds": 0.0006387999746948481,
        "mean_model_fit_seconds": 0.00025510002160444856,
        "garch_fit_seconds": 0.0,
        "garch_forecast_seconds": 0.19610480003757402,
        "monte_carlo_seconds": 0.004093399969860911,
        "forecast_loop_seconds": 0.009261300030630082,
        "total_seconds": 0.4358557999948971
      },
      "mean_model": {
        "name": "regime_mean_reversion",
        "class": "MeanReversionForecaster"
      },
      "vol_model": {
        "class": "EGARCHVolModel",
        "distribution": "Student-t",
        "degrees_of_freedom": 6.0,
        "skew": -0.8,
        "forecast_method": "simulation",
        "sigma_last": 0.005
      },
      "environment": {
        "python": "3.12.10",
        "numpy": "1.26.4",
        "pandas": "2.3.3",
        "platform": "Windows-11-10.0.26200-SP0"
      },
      "regime": {
        "enabled": true,
        "label": "RANGE",
        "confidence": 0.9456866076361609,
        "lookback": 200,
        "route": "alternate"
      },
      "residual_std": 0.0033935159857953444,
      "last_price": 114756.98,
      "execution_price": 114756.98,
      "price_modeling": 114756.98,
      "price_execution": 114756.98,
      "execution_price_source": "client",
      "sigma_path_min": 0.005,
      "sigma_path_max": 0.005,
      "backtest_time_travel": true,
      "backtest_time_travel_model": "nhits"
    },
    "model_status": {
      "model_type": "nhits",
      "device": "cuda",
      "mean": {
        "loaded": true,
        "reason": "time_travel_cache"
      },
      "vol": {
        "loaded": false,
        "reason": "time_travel_cache"
      }
    },
    "total_seconds": 0.438
  }
}