{
  "status": "success",
  "elapsed_sec": 0.31,
  "data": {
    "ok": true,
    "status": "ok",
    "message": "forecast completed",
    "request_id": "bca33929-c480-4b1e-af1f-3d85870c7081",
    "timestamp": "2026-02-24T04:36:31Z",
    "request": {
      "symbol": "BTC/USD",
      "timeframe": "1h",
      "horizons": [
        24
      ],
      "use_montecarlo": true,
      "paths": 1000,
      "trade_mode": "forward",
      "include_predictions": true,
      "include_metadata": true,
      "include_model_info": true,
      "execution_price": 101810.83
    },
    "warnings": [],
    "data": {
      "payload": {
        "symbol": "BTC/USD",
        "asOf": "2025-06-21T22:00:00+00:00",
        "timeframe": "1h",
        "use_montecarlo": true,
        "horizons": [
          {
            "h": "24h",
            "direction": "long",
            "trade_mode": "forward",
            "entry_price": 102519.6962211688,
            "entry_type": "conditional_forecast",
            "entry_method": "median",
            "forecast": {
              "medianPrice": 102519.6962211688,
              "p20": 100189.12125854082,
              "p80": 103830.08535529791
            },
            "tp": 103830.08535529791,
            "sl": 100189.12125854082,
            "riskReward": 0.5623,
            "prob_hit_tp_before_sl": 0.225,
            "confidence": 0.6441,
            "position_size": 1.0,
            "model": {
              "mean": "NHITS",
              "vol": "EGARCH_t",
              "calibrated": true
            }
          }
        ],
        "entry_price": 102519.6962211688
      },
      "as_of": "2025-06-21T22:00:00+00:00",
      "data_hash": "4932213a29629838293452a3808f1d521e85c28afde2ba955f0fc528c9ec3bbc",
      "durations": {
        "fetch_seconds": 0.0006467999774031341,
        "mean_model_fit_seconds": 0.0,
        "garch_fit_seconds": 0.0,
        "garch_forecast_seconds": 0.12499630003003404,
        "monte_carlo_seconds": 0.0034598999191075563,
        "forecast_loop_seconds": 0.057734399975743145,
        "total_seconds": 0.3114542000112124
      }
    },
    "metadata": {
      "symbol": "BTC/USD",
      "timeframe": "1h",
      "horizons": [
        24
      ],
      "timestamp": "2026-02-24T04:36:31Z",
      "timestamp_slug": "20260224T043631Z",
      "as_of": "2025-06-21T22:00:00+00:00",
      "n_observations": 132,
      "data_hash": "4932213a29629838293452a3808f1d521e85c28afde2ba955f0fc528c9ec3bbc",
      "use_montecarlo": true,
      "monte_carlo_paths": 200,
      "durations": {
        "fetch_seconds": 0.0006467999774031341,
        "mean_model_fit_seconds": 0.0,
        "garch_fit_seconds": 0.0,
        "garch_forecast_seconds": 0.12499630003003404,
        "monte_carlo_seconds": 0.0034598999191075563,
        "forecast_loop_seconds": 0.057734399975743145,
        "total_seconds": 0.3114542000112124
      },
      "mean_model": {
        "name": "NHITS",
        "class": "NHiTSForecaster",
        "backend_class": "NHiTSModel",
        "hyperparameters": {
          "output_chunk_shift": 0,
          "num_stacks": 3,
          "num_blocks": 1,
          "num_layers": 2,
          "layer_widths": 512,
          "pooling_kernel_sizes": null,
          "n_freq_downsample": null,
          "dropout": 0.1,
          "activation": "ReLU",
          "MaxPool1d": true,
          "input_chunk_length": 48,
          "output_chunk_length": 24,
          "n_epochs": 150,
          "batch_size": 20000,
          "random_state": 42,
          "loss_fn": {
            "training": false,
            "reduction": "mean",
            "beta": 1.0
          },
          "optimizer_kwargs": {
            "lr": 0.001
          },
          "pl_trainer_kwargs": {
            "accelerator": "gpu",
            "devices": 1
          }
        }
      },
      "vol_model": {
        "class": "EGARCHVolModel",
        "distribution": "Student-t",
        "degrees_of_freedom": 6.0,
        "skew": -0.8,
        "forecast_method": "simulation",
        "sigma_last": 0.005
      },
      "environment": {
        "python": "3.12.10",
        "numpy": "1.26.4",
        "pandas": "2.3.3",
        "platform": "Windows-11-10.0.26200-SP0"
      },
      "regime": {
        "enabled": true,
        "label": "TREND_DOWN",
        "confidence": 2.0068078785365076e-23,
        "lookback": 200,
        "route": "trend"
      },
      "residual_std": 0.003517852727813499,
      "last_price": 101810.83,
      "execution_price": 101810.83,
      "price_modeling": 101810.83,
      "price_execution": 101810.83,
      "execution_price_source": "client",
      "sigma_path_min": 0.005,
      "sigma_path_max": 0.005,
      "backtest_time_travel": true,
      "backtest_time_travel_model": "nhits"
    },
    "model_status": {
      "model_type": "nhits",
      "device": "cuda",
      "mean": {
        "loaded": true,
        "reason": "time_travel_cache"
      },
      "vol": {
        "loaded": false,
        "reason": "time_travel_cache"
      }
    },
    "total_seconds": 0.313
  }
}