{
  "status": "success",
  "elapsed_sec": 0.25,
  "data": {
    "ok": true,
    "status": "ok",
    "message": "forecast completed",
    "request_id": "913fdbbf-734c-4c92-8e90-e451304109b3",
    "timestamp": "2026-02-24T03:51:18Z",
    "request": {
      "symbol": "BTC/USD",
      "timeframe": "1h",
      "horizons": [
        24
      ],
      "use_montecarlo": true,
      "paths": 1000,
      "trade_mode": "forward",
      "include_predictions": true,
      "include_metadata": true,
      "include_model_info": true,
      "execution_price": 116596.43
    },
    "warnings": [],
    "data": {
      "payload": {
        "symbol": "BTC/USD",
        "asOf": "2025-08-07T18:00:00+00:00",
        "timeframe": "1h",
        "use_montecarlo": true,
        "horizons": [
          {
            "h": "24h",
            "direction": "long",
            "trade_mode": "forward",
            "entry_price": 118706.52555593218,
            "entry_type": "conditional_forecast",
            "entry_method": "median",
            "forecast": {
              "medianPrice": 118706.52555593218,
              "p20": 116556.60779366843,
              "p80": 120471.58036382485
            },
            "tp": 120471.58036382485,
            "sl": 116556.60779366843,
            "riskReward": 0.821,
            "prob_hit_tp_before_sl": 0.415,
            "confidence": 0.6441,
            "position_size": 1.0,
            "model": {
              "mean": "regime_momentum",
              "vol": "EGARCH_t",
              "calibrated": true
            }
          }
        ],
        "entry_price": 118706.52555593218
      },
      "as_of": "2025-08-07T18:00:00+00:00",
      "data_hash": "f4ba297652c35e763efbe465d731e38a500b8a8831110ce1ed4794071e4525a8",
      "durations": {
        "fetch_seconds": 0.000354000017978251,
        "mean_model_fit_seconds": 0.0004026999813504517,
        "garch_fit_seconds": 0.0,
        "garch_forecast_seconds": 0.10827929998049513,
        "monte_carlo_seconds": 0.002394900016952306,
        "forecast_loop_seconds": 0.0051531000062823296,
        "total_seconds": 0.2509975000284612
      }
    },
    "metadata": {
      "symbol": "BTC/USD",
      "timeframe": "1h",
      "horizons": [
        24
      ],
      "timestamp": "2026-02-24T03:51:18Z",
      "timestamp_slug": "20260224T035118Z",
      "as_of": "2025-08-07T18:00:00+00:00",
      "n_observations": 256,
      "data_hash": "f4ba297652c35e763efbe465d731e38a500b8a8831110ce1ed4794071e4525a8",
      "use_montecarlo": true,
      "monte_carlo_paths": 200,
      "durations": {
        "fetch_seconds": 0.000354000017978251,
        "mean_model_fit_seconds": 0.0004026999813504517,
        "garch_fit_seconds": 0.0,
        "garch_forecast_seconds": 0.10827929998049513,
        "monte_carlo_seconds": 0.002394900016952306,
        "forecast_loop_seconds": 0.0051531000062823296,
        "total_seconds": 0.2509975000284612
      },
      "mean_model": {
        "name": "regime_momentum",
        "class": "MomentumForecaster"
      },
      "vol_model": {
        "class": "EGARCHVolModel",
        "distribution": "Student-t",
        "degrees_of_freedom": 6.0,
        "skew": -0.8,
        "forecast_method": "simulation",
        "sigma_last": 0.005
      },
      "environment": {
        "python": "3.12.10",
        "numpy": "1.26.4",
        "pandas": "2.3.3",
        "platform": "Windows-11-10.0.26200-SP0"
      },
      "regime": {
        "enabled": true,
        "label": "BREAKOUT_VOL_EXPANSION",
        "confidence": 0.9456864868091435,
        "lookback": 200,
        "route": "alternate"
      },
      "residual_std": 0.0030485217042215654,
      "last_price": 116596.43,
      "execution_price": 116596.43,
      "price_modeling": 116596.43,
      "price_execution": 116596.43,
      "execution_price_source": "client",
      "sigma_path_min": 0.005,
      "sigma_path_max": 0.005,
      "backtest_time_travel": true,
      "backtest_time_travel_model": "nhits"
    },
    "model_status": {
      "model_type": "nhits",
      "device": "cuda",
      "mean": {
        "loaded": true,
        "reason": "time_travel_cache"
      },
      "vol": {
        "loaded": false,
        "reason": "time_travel_cache"
      }
    },
    "total_seconds": 0.253
  }
}